{"season":12,"week":3,"date":"2017-04-23","team1":"MLC","team2":"MACP","game1":{"map":"Cedar","scores":{"t1h1":3,"t1h2":5,"t1ot":0,"t2h1":8,"t2h2":4,"t2ot":0},"links":{"h1":["https://tagpro.eu/?match=1363172"],"h2":["https://tagpro.eu/?match=1363214"],"ot":[]},"stats":{"h1":{"danisk":{"score":25,"team":"MLC","grabs":19,"pops":19,"drops":18,"hold":91,"captures":0,"prevent":31,"ndpops":1,"returns":13,"tags":16,"pups":1,"minutes":10,"goregrab":4,"longholds":0,"goodhandoff":3,"handoff":8,"coregrab":0,"retinbase":6,"nrtags":3,"holdagainst":230,"pupscomp":27,"pm":-5,"quickret":4,"flaccids":4,"gohandoff":3,"keyret":1,"saves":0,"cohandoff":0,"capspm":0,"holdpm":9.1,"grabspm":1.9,"score%":0,"holdpgrab":4.7894736842105265,"spark%":0.375,"flcd%":0.21052631578947367,"tagspm":1.6,"retpm":1.3,"prepm":3.1,"hapm":23,"prepret":2.3846153846153846,"prepha":0.13478260869565217,"rib%":0.46153846153846156,"qr%":0.3076923076923077,"nrtpm":0.3,"kd":0.8421052631578947,"kf":1,"pup%":0.037037037037037035},"CB13":{"score":35,"team":"MLC","grabs":7,"pops":12,"drops":6,"hold":16,"captures":1,"prevent":168,"ndpops":6,"returns":12,"tags":13,"pups":2,"minutes":10,"goregrab":2,"longholds":0,"goodhandoff":0,"handoff":0,"coregrab":1,"retinbase":7,"nrtags":1,"holdagainst":230,"pupscomp":27,"pm":-5,"quickret":6,"flaccids":5,"gohandoff":0,"keyret":0,"saves":0,"cohandoff":0,"capspm":0.1,"holdpm":1.6,"grabspm":0.7,"score%":0.14285714285714285,"holdpgrab":2.2857142857142856,"spark%":0,"flcd%":0.7142857142857143,"tagspm":1.3,"retpm":1.2,"prepm":16.8,"hapm":23,"prepret":14,"prepha":0.7304347826086957,"rib%":0.5833333333333334,"qr%":0.5,"nrtpm":0.1,"kd":1.0833333333333333,"kf":0,"pup%":0.07407407407407407},"sIide":{"score":49,"team":"MACP","grabs":6,"pops":8,"drops":6,"hold":21,"captures":0,"prevent":198,"ndpops":2,"returns":21,"tags":25,"pups":5,"minutes":10,"goregrab":1,"longholds":0,"goodhandoff":2,"handoff":2,"coregrab":0,"retinbase":7,"nrtags":4,"holdagainst":219,"pupscomp":27,"pm":5,"quickret":5,"flaccids":3,"gohandoff":0,"keyret":1,"saves":1,"cohandoff":0,"capspm":0,"holdpm":2.1,"grabspm":0.6,"score%":0,"holdpgrab":3.5,"spark%":1,"flcd%":0.5,"tagspm":2.5,"retpm":2.1,"prepm":19.8,"hapm":21.9,"prepret":9.428571428571429,"prepha":0.9041095890410958,"rib%":0.3333333333333333,"qr%":0.23809523809523808,"nrtpm":0.4,"kd":3.125,"kf":0,"pup%":0.18518518518518517},"#Frozen":{"score":20,"team":"MLC","grabs":13,"pops":17,"drops":12,"hold":60,"captures":1,"prevent":57,"ndpops":5,"returns":4,"tags":4,"pups":3,"minutes":10,"goregrab":3,"longholds":0,"goodhandoff":5,"handoff":7,"coregrab":0,"retinbase":1,"nrtags":0,"holdagainst":230,"pupscomp":27,"pm":-5,"quickret":1,"flaccids":5,"gohandoff":1,"keyret":0,"saves":0,"cohandoff":0,"capspm":0.1,"holdpm":6,"grabspm":1.3,"score%":0.07692307692307693,"holdpgrab":4.615384615384615,"spark%":0.7142857142857143,"flcd%":0.38461538461538464,"tagspm":0.4,"retpm":0.4,"prepm":5.7,"hapm":23,"prepret":14.25,"prepha":0.24782608695652175,"rib%":0.25,"qr%":0.25,"nrtpm":0,"kd":0.23529411764705882,"kf":0,"pup%":0.1111111111111111},"Gman8181":{"score":53,"team":"MACP","grabs":19,"pops":14,"drops":12,"hold":94,"captures":6,"prevent":58,"ndpops":2,"returns":4,"tags":6,"pups":2,"minutes":10,"goregrab":8,"longholds":0,"goodhandoff":3,"handoff":5,"coregrab":1,"retinbase":1,"nrtags":2,"holdagainst":219,"pupscomp":27,"pm":5,"quickret":1,"flaccids":4,"gohandoff":2,"keyret":0,"saves":0,"cohandoff":2,"capspm":0.6,"holdpm":9.4,"grabspm":1.9,"score%":0.3157894736842105,"holdpgrab":4.947368421052632,"spark%":0.6,"flcd%":0.21052631578947367,"tagspm":0.6,"retpm":0.4,"prepm":5.8,"hapm":21.9,"prepret":14.5,"prepha":0.2648401826484018,"rib%":0.25,"qr%":0.25,"nrtpm":0.2,"kd":0.42857142857142855,"kf":1,"pup%":0.07407407407407407},"Fatal":{"score":40,"team":"MLC","grabs":7,"pops":12,"drops":6,"hold":52,"captures":1,"prevent":211,"ndpops":6,"returns":12,"tags":13,"pups":3,"minutes":10,"goregrab":0,"longholds":0,"goodhandoff":1,"handoff":2,"coregrab":0,"retinbase":8,"nrtags":1,"holdagainst":230,"pupscomp":27,"pm":-5,"quickret":7,"flaccids":2,"gohandoff":2,"keyret":0,"saves":0,"cohandoff":1,"capspm":0.1,"holdpm":5.2,"grabspm":0.7,"score%":0.14285714285714285,"holdpgrab":7.428571428571429,"spark%":0.5,"flcd%":0.2857142857142857,"tagspm":1.3,"retpm":1.2,"prepm":21.1,"hapm":23,"prepret":17.583333333333332,"prepha":0.9173913043478261,"rib%":0.6666666666666666,"qr%":0.5833333333333334,"nrtpm":0.1,"kd":1.0833333333333333,"kf":0,"pup%":0.1111111111111111},"Dalek":{"score":42,"team":"MACP","grabs":8,"pops":11,"drops":8,"hold":38,"captures":0,"prevent":149,"ndpops":3,"returns":13,"tags":19,"pups":5,"minutes":10,"goregrab":3,"longholds":1,"goodhandoff":1,"handoff":1,"coregrab":0,"retinbase":9,"nrtags":6,"holdagainst":219,"pupscomp":27,"pm":5,"quickret":10,"flaccids":3,"gohandoff":0,"keyret":0,"saves":0,"cohandoff":0,"capspm":0,"holdpm":3.8,"grabspm":0.8,"score%":0,"holdpgrab":4.75,"spark%":1,"flcd%":0.375,"tagspm":1.9,"retpm":1.3,"prepm":14.9,"hapm":21.9,"prepret":11.461538461538462,"prepha":0.680365296803653,"rib%":0.6923076923076923,"qr%":0.7692307692307693,"nrtpm":0.6,"kd":1.7272727272727273,"kf":0,"pup%":0.18518518518518517},"dywz":{"score":36,"team":"MACP","grabs":18,"pops":18,"drops":16,"hold":77,"captures":2,"prevent":45,"ndpops":2,"returns":4,"tags":6,"pups":6,"minutes":10,"goregrab":3,"longholds":0,"goodhandoff":2,"handoff":4,"coregrab":0,"retinbase":0,"nrtags":2,"holdagainst":219,"pupscomp":27,"pm":5,"quickret":0,"flaccids":8,"gohandoff":5,"keyret":0,"saves":0,"cohandoff":0,"capspm":0.2,"holdpm":7.7,"grabspm":1.8,"score%":0.1111111111111111,"holdpgrab":4.277777777777778,"spark%":0.5,"flcd%":0.4444444444444444,"tagspm":0.6,"retpm":0.4,"prepm":4.5,"hapm":21.9,"prepret":11.25,"prepha":0.2054794520547945,"rib%":0,"qr%":0,"nrtpm":0.2,"kd":0.3333333333333333,"kf":0,"pup%":0.2222222222222222}},"h2":{"danisk":{"score":28,"team":"MLC","grabs":13,"pops":12,"drops":12,"hold":108,"captures":1,"prevent":4,"ndpops":0,"returns":6,"tags":10,"pups":2,"minutes":10,"goregrab":4,"longholds":1,"goodhandoff":2,"handoff":2,"coregrab":0,"retinbase":0,"nrtags":4,"holdagainst":267,"pupscomp":27,"pm":1,"quickret":0,"flaccids":4,"gohandoff":3,"keyret":0,"saves":0,"cohandoff":0,"capspm":0.1,"holdpm":10.8,"grabspm":1.3,"score%":0.07692307692307693,"holdpgrab":8.307692307692308,"spark%":1,"flcd%":0.3076923076923077,"tagspm":1,"retpm":0.6,"prepm":0.4,"hapm":26.7,"prepret":0.6666666666666666,"prepha":0.0149812734082397,"rib%":0,"qr%":0,"nrtpm":0.4,"kd":0.8333333333333334,"kf":0,"pup%":0.07407407407407407},"dywz":{"score":30,"team":"MACP","grabs":16,"pops":17,"drops":15,"hold":135,"captures":1,"prevent":38,"ndpops":2,"returns":3,"tags":7,"pups":3,"minutes":10,"goregrab":2,"longholds":1,"goodhandoff":4,"handoff":5,"coregrab":0,"retinbase":1,"nrtags":4,"holdagainst":271,"pupscomp":27,"pm":-1,"quickret":1,"flaccids":4,"gohandoff":3,"keyret":1,"saves":0,"cohandoff":0,"capspm":0.1,"holdpm":13.5,"grabspm":1.6,"score%":0.0625,"holdpgrab":8.4375,"spark%":0.8,"flcd%":0.25,"tagspm":0.7,"retpm":0.3,"prepm":3.8,"hapm":27.1,"prepret":12.666666666666666,"prepha":0.14022140221402213,"rib%":0.3333333333333333,"qr%":0.3333333333333333,"nrtpm":0.4,"kd":0.4117647058823529,"kf":0,"pup%":0.1111111111111111},"Gman8181":{"score":22,"team":"MACP","grabs":15,"pops":16,"drops":13,"hold":94,"captures":2,"prevent":31,"ndpops":3,"returns":3,"tags":3,"pups":1,"minutes":10,"goregrab":3,"longholds":0,"goodhandoff":4,"handoff":7,"coregrab":0,"retinbase":2,"nrtags":0,"holdagainst":271,"pupscomp":27,"pm":-1,"quickret":1,"flaccids":3,"gohandoff":1,"keyret":0,"saves":0,"cohandoff":0,"capspm":0.2,"holdpm":9.4,"grabspm":1.5,"score%":0.13333333333333333,"holdpgrab":6.266666666666667,"spark%":0.5714285714285714,"flcd%":0.2,"tagspm":0.3,"retpm":0.3,"prepm":3.1,"hapm":27.1,"prepret":10.333333333333334,"prepha":0.11439114391143912,"rib%":0.6666666666666666,"qr%":0.3333333333333333,"nrtpm":0,"kd":0.1875,"kf":0,"pup%":0.037037037037037035},"#Frozen":{"score":39,"team":"MLC","grabs":16,"pops":18,"drops":13,"hold":93,"captures":2,"prevent":33,"ndpops":5,"returns":7,"tags":10,"pups":6,"minutes":10,"goregrab":2,"longholds":1,"goodhandoff":7,"handoff":8,"coregrab":1,"retinbase":4,"nrtags":3,"holdagainst":267,"pupscomp":27,"pm":1,"quickret":2,"flaccids":5,"gohandoff":1,"keyret":0,"saves":0,"cohandoff":0,"capspm":0.2,"holdpm":9.3,"grabspm":1.6,"score%":0.125,"holdpgrab":5.8125,"spark%":0.875,"flcd%":0.3125,"tagspm":1,"retpm":0.7,"prepm":3.3,"hapm":26.7,"prepret":4.714285714285714,"prepha":0.12359550561797752,"rib%":0.5714285714285714,"qr%":0.2857142857142857,"nrtpm":0.3,"kd":0.5555555555555556,"kf":1,"pup%":0.2222222222222222},"Fatal":{"score":54,"team":"MLC","grabs":9,"pops":10,"drops":7,"hold":42,"captures":2,"prevent":181,"ndpops":3,"returns":10,"tags":14,"pups":6,"minutes":10,"goregrab":3,"longholds":0,"goodhandoff":0,"handoff":0,"coregrab":1,"retinbase":7,"nrtags":4,"holdagainst":267,"pupscomp":27,"pm":1,"quickret":6,"flaccids":4,"gohandoff":0,"keyret":0,"saves":0,"cohandoff":0,"capspm":0.2,"holdpm":4.2,"grabspm":0.9,"score%":0.2222222222222222,"holdpgrab":4.666666666666667,"spark%":0,"flcd%":0.4444444444444444,"tagspm":1.4,"retpm":1,"prepm":18.1,"hapm":26.7,"prepret":18.1,"prepha":0.6779026217228464,"rib%":0.7,"qr%":0.6,"nrtpm":0.4,"kd":1.4,"kf":0,"pup%":0.2222222222222222},"sIide":{"score":41,"team":"MACP","grabs":6,"pops":11,"drops":6,"hold":19,"captures":0,"prevent":163,"ndpops":5,"returns":16,"tags":20,"pups":4,"minutes":10,"goregrab":2,"longholds":0,"goodhandoff":1,"handoff":2,"coregrab":0,"retinbase":10,"nrtags":4,"holdagainst":271,"pupscomp":27,"pm":-1,"quickret":9,"flaccids":2,"gohandoff":1,"keyret":1,"saves":0,"cohandoff":0,"capspm":0,"holdpm":1.9,"grabspm":0.6,"score%":0,"holdpgrab":3.1666666666666665,"spark%":0.5,"flcd%":0.3333333333333333,"tagspm":2,"retpm":1.6,"prepm":16.3,"hapm":27.1,"prepret":10.1875,"prepha":0.6014760147601476,"rib%":0.625,"qr%":0.5625,"nrtpm":0.4,"kd":1.8181818181818181,"kf":0,"pup%":0.14814814814814814},"Dalek":{"score":42,"team":"MACP","grabs":7,"pops":8,"drops":5,"hold":19,"captures":1,"prevent":197,"ndpops":3,"returns":14,"tags":14,"pups":2,"minutes":10,"goregrab":4,"longholds":0,"goodhandoff":0,"handoff":0,"coregrab":1,"retinbase":4,"nrtags":0,"holdagainst":271,"pupscomp":27,"pm":-1,"quickret":4,"flaccids":4,"gohandoff":1,"keyret":0,"saves":0,"cohandoff":0,"capspm":0.1,"holdpm":1.9,"grabspm":0.7,"score%":0.14285714285714285,"holdpgrab":2.7142857142857144,"spark%":0,"flcd%":0.5714285714285714,"tagspm":1.4,"retpm":1.4,"prepm":19.7,"hapm":27.1,"prepret":14.071428571428571,"prepha":0.7269372693726938,"rib%":0.2857142857142857,"qr%":0.2857142857142857,"nrtpm":0,"kd":1.75,"kf":1,"pup%":0.07407407407407407},"CB13":{"score":44,"team":"MLC","grabs":4,"pops":6,"drops":4,"hold":28,"captures":0,"prevent":186,"ndpops":2,"returns":16,"tags":18,"pups":3,"minutes":10,"goregrab":0,"longholds":1,"goodhandoff":0,"handoff":2,"coregrab":0,"retinbase":6,"nrtags":2,"holdagainst":267,"pupscomp":27,"pm":1,"quickret":5,"flaccids":2,"gohandoff":0,"keyret":1,"saves":0,"cohandoff":0,"capspm":0,"holdpm":2.8,"grabspm":0.4,"score%":0,"holdpgrab":7,"spark%":0,"flcd%":0.5,"tagspm":1.8,"retpm":1.6,"prepm":18.6,"hapm":26.7,"prepret":11.625,"prepha":0.6966292134831461,"rib%":0.375,"qr%":0.3125,"nrtpm":0.2,"kd":3,"kf":0,"pup%":0.1111111111111111}},"ot":{},"total":{"danisk":{"score":53,"team":"MLC","grabs":32,"pops":31,"drops":30,"hold":199,"captures":1,"prevent":35,"ndpops":1,"returns":19,"tags":26,"pups":3,"minutes":20,"goregrab":8,"longholds":1,"goodhandoff":5,"handoff":10,"coregrab":0,"retinbase":6,"nrtags":7,"holdagainst":497,"pupscomp":54,"pm":-4,"quickret":4,"flaccids":8,"gohandoff":6,"keyret":1,"saves":0,"cohandoff":0,"capspm":0.05,"holdpm":9.95,"grabspm":1.6,"score%":0.03125,"holdpgrab":6.21875,"spark%":0.5,"flcd%":0.25,"tagspm":1.3,"retpm":0.95,"prepm":1.75,"hapm":24.85,"prepret":1.8421052631578947,"prepha":0.07042253521126761,"rib%":0.3157894736842105,"qr%":0.21052631578947367,"nrtpm":0.35,"kd":0.8387096774193549,"kf":1,"pup%":0.05555555555555555},"CB13":{"score":79,"team":"MLC","grabs":11,"pops":18,"drops":10,"hold":44,"captures":1,"prevent":354,"ndpops":8,"returns":28,"tags":31,"pups":5,"minutes":20,"goregrab":2,"longholds":1,"goodhandoff":0,"handoff":2,"coregrab":1,"retinbase":13,"nrtags":3,"holdagainst":497,"pupscomp":54,"pm":-4,"quickret":11,"flaccids":7,"gohandoff":0,"keyret":1,"saves":0,"cohandoff":0,"capspm":0.05,"holdpm":2.2,"grabspm":0.55,"score%":0.09090909090909091,"holdpgrab":4,"spark%":0,"flcd%":0.6363636363636364,"tagspm":1.55,"retpm":1.4,"prepm":17.7,"hapm":24.85,"prepret":12.642857142857142,"prepha":0.7122736418511066,"rib%":0.4642857142857143,"qr%":0.39285714285714285,"nrtpm":0.15,"kd":1.7222222222222223,"kf":0,"pup%":0.09259259259259259},"sIide":{"score":90,"team":"MACP","grabs":12,"pops":19,"drops":12,"hold":40,"captures":0,"prevent":361,"ndpops":7,"returns":37,"tags":45,"pups":9,"minutes":20,"goregrab":3,"longholds":0,"goodhandoff":3,"handoff":4,"coregrab":0,"retinbase":17,"nrtags":8,"holdagainst":490,"pupscomp":54,"pm":4,"quickret":14,"flaccids":5,"gohandoff":1,"keyret":2,"saves":1,"cohandoff":0,"capspm":0,"holdpm":2,"grabspm":0.6,"score%":0,"holdpgrab":3.3333333333333335,"spark%":0.75,"flcd%":0.4166666666666667,"tagspm":2.25,"retpm":1.85,"prepm":18.05,"hapm":24.5,"prepret":9.756756756756756,"prepha":0.736734693877551,"rib%":0.4594594594594595,"qr%":0.3783783783783784,"nrtpm":0.4,"kd":2.3684210526315788,"kf":0,"pup%":0.16666666666666666},"#Frozen":{"score":59,"team":"MLC","grabs":29,"pops":35,"drops":25,"hold":153,"captures":3,"prevent":90,"ndpops":10,"returns":11,"tags":14,"pups":9,"minutes":20,"goregrab":5,"longholds":1,"goodhandoff":12,"handoff":15,"coregrab":1,"retinbase":5,"nrtags":3,"holdagainst":497,"pupscomp":54,"pm":-4,"quickret":3,"flaccids":10,"gohandoff":2,"keyret":0,"saves":0,"cohandoff":0,"capspm":0.15,"holdpm":7.65,"grabspm":1.45,"score%":0.10344827586206896,"holdpgrab":5.275862068965517,"spark%":0.8,"flcd%":0.3448275862068966,"tagspm":0.7,"retpm":0.55,"prepm":4.5,"hapm":24.85,"prepret":8.181818181818182,"prepha":0.18108651911468812,"rib%":0.45454545454545453,"qr%":0.2727272727272727,"nrtpm":0.15,"kd":0.4,"kf":1,"pup%":0.16666666666666666},"Gman8181":{"score":75,"team":"MACP","grabs":34,"pops":30,"drops":25,"hold":188,"captures":8,"prevent":89,"ndpops":5,"returns":7,"tags":9,"pups":3,"minutes":20,"goregrab":11,"longholds":0,"goodhandoff":7,"handoff":12,"coregrab":1,"retinbase":3,"nrtags":2,"holdagainst":490,"pupscomp":54,"pm":4,"quickret":2,"flaccids":7,"gohandoff":3,"keyret":0,"saves":0,"cohandoff":2,"capspm":0.4,"holdpm":9.4,"grabspm":1.7,"score%":0.23529411764705882,"holdpgrab":5.529411764705882,"spark%":0.5833333333333334,"flcd%":0.20588235294117646,"tagspm":0.45,"retpm":0.35,"prepm":4.45,"hapm":24.5,"prepret":12.714285714285714,"prepha":0.1816326530612245,"rib%":0.42857142857142855,"qr%":0.2857142857142857,"nrtpm":0.1,"kd":0.3,"kf":1,"pup%":0.05555555555555555},"Fatal":{"score":94,"team":"MLC","grabs":16,"pops":22,"drops":13,"hold":94,"captures":3,"prevent":392,"ndpops":9,"returns":22,"tags":27,"pups":9,"minutes":20,"goregrab":3,"longholds":0,"goodhandoff":1,"handoff":2,"coregrab":1,"retinbase":15,"nrtags":5,"holdagainst":497,"pupscomp":54,"pm":-4,"quickret":13,"flaccids":6,"gohandoff":2,"keyret":0,"saves":0,"cohandoff":1,"capspm":0.15,"holdpm":4.7,"grabspm":0.8,"score%":0.1875,"holdpgrab":5.875,"spark%":0.5,"flcd%":0.375,"tagspm":1.35,"retpm":1.1,"prepm":19.6,"hapm":24.85,"prepret":17.818181818181817,"prepha":0.7887323943661971,"rib%":0.6818181818181818,"qr%":0.5909090909090909,"nrtpm":0.25,"kd":1.2272727272727273,"kf":0,"pup%":0.16666666666666666},"Dalek":{"score":84,"team":"MACP","grabs":15,"pops":19,"drops":13,"hold":57,"captures":1,"prevent":346,"ndpops":6,"returns":27,"tags":33,"pups":7,"minutes":20,"goregrab":7,"longholds":1,"goodhandoff":1,"handoff":1,"coregrab":1,"retinbase":13,"nrtags":6,"holdagainst":490,"pupscomp":54,"pm":4,"quickret":14,"flaccids":7,"gohandoff":1,"keyret":0,"saves":0,"cohandoff":0,"capspm":0.05,"holdpm":2.85,"grabspm":0.75,"score%":0.06666666666666667,"holdpgrab":3.8,"spark%":1,"flcd%":0.4666666666666667,"tagspm":1.65,"retpm":1.35,"prepm":17.3,"hapm":24.5,"prepret":12.814814814814815,"prepha":0.7061224489795919,"rib%":0.48148148148148145,"qr%":0.5185185185185185,"nrtpm":0.3,"kd":1.736842105263158,"kf":1,"pup%":0.12962962962962962},"dywz":{"score":66,"team":"MACP","grabs":34,"pops":35,"drops":31,"hold":212,"captures":3,"prevent":83,"ndpops":4,"returns":7,"tags":13,"pups":9,"minutes":20,"goregrab":5,"longholds":1,"goodhandoff":6,"handoff":9,"coregrab":0,"retinbase":1,"nrtags":6,"holdagainst":490,"pupscomp":54,"pm":4,"quickret":1,"flaccids":12,"gohandoff":8,"keyret":1,"saves":0,"cohandoff":0,"capspm":0.15,"holdpm":10.6,"grabspm":1.7,"score%":0.08823529411764706,"holdpgrab":6.235294117647059,"spark%":0.6666666666666666,"flcd%":0.35294117647058826,"tagspm":0.65,"retpm":0.35,"prepm":4.15,"hapm":24.5,"prepret":11.857142857142858,"prepha":0.16938775510204082,"rib%":0.14285714285714285,"qr%":0.14285714285714285,"nrtpm":0.3,"kd":0.37142857142857144,"kf":0,"pup%":0.16666666666666666}}}},"game2":{"map":"Scorpio","scores":{"t1h1":3,"t1h2":3,"t1ot":0,"t2h1":2,"t2h2":1,"t2ot":0},"links":{"h1":["https://tagpro.eu/?match=1363239"],"h2":["https://tagpro.eu/?match=1363265"],"ot":[]},"stats":{"h1":{"danisk":{"score":25,"team":"MACP","grabs":19,"pops":19,"drops":18,"hold":91,"captures":0,"prevent":31,"ndpops":1,"returns":13,"tags":16,"pups":1,"minutes":10,"goregrab":4,"longholds":0,"goodhandoff":3,"handoff":8,"coregrab":0,"retinbase":6,"nrtags":3,"holdagainst":230,"pupscomp":27,"pm":-5,"quickret":4,"flaccids":4,"gohandoff":3,"keyret":1,"saves":0,"cohandoff":0,"capspm":0,"holdpm":9.1,"grabspm":1.9,"score%":0,"holdpgrab":4.7894736842105265,"spark%":0.375,"flcd%":0.21052631578947367,"tagspm":1.6,"retpm":1.3,"prepm":3.1,"hapm":23,"prepret":2.3846153846153846,"prepha":0.13478260869565217,"rib%":0.46153846153846156,"qr%":0.3076923076923077,"nrtpm":0.3,"kd":0.8421052631578947,"kf":1,"pup%":0.037037037037037035},"CB13":{"score":35,"team":"MACP","grabs":7,"pops":12,"drops":6,"hold":16,"captures":1,"prevent":168,"ndpops":6,"returns":12,"tags":13,"pups":2,"minutes":10,"goregrab":2,"longholds":0,"goodhandoff":0,"handoff":0,"coregrab":1,"retinbase":7,"nrtags":1,"holdagainst":230,"pupscomp":27,"pm":-5,"quickret":6,"flaccids":5,"gohandoff":0,"keyret":0,"saves":0,"cohandoff":0,"capspm":0.1,"holdpm":1.6,"grabspm":0.7,"score%":0.14285714285714285,"holdpgrab":2.2857142857142856,"spark%":0,"flcd%":0.7142857142857143,"tagspm":1.3,"retpm":1.2,"prepm":16.8,"hapm":23,"prepret":14,"prepha":0.7304347826086957,"rib%":0.5833333333333334,"qr%":0.5,"nrtpm":0.1,"kd":1.0833333333333333,"kf":0,"pup%":0.07407407407407407},"sIide":{"score":49,"team":"MACP","grabs":6,"pops":8,"drops":6,"hold":21,"captures":0,"prevent":198,"ndpops":2,"returns":21,"tags":25,"pups":5,"minutes":10,"goregrab":1,"longholds":0,"goodhandoff":2,"handoff":2,"coregrab":0,"retinbase":7,"nrtags":4,"holdagainst":219,"pupscomp":27,"pm":5,"quickret":5,"flaccids":3,"gohandoff":0,"keyret":1,"saves":1,"cohandoff":0,"capspm":0,"holdpm":2.1,"grabspm":0.6,"score%":0,"holdpgrab":3.5,"spark%":1,"flcd%":0.5,"tagspm":2.5,"retpm":2.1,"prepm":19.8,"hapm":21.9,"prepret":9.428571428571429,"prepha":0.9041095890410958,"rib%":0.3333333333333333,"qr%":0.23809523809523808,"nrtpm":0.4,"kd":3.125,"kf":0,"pup%":0.18518518518518517},"#Frozen":{"score":20,"team":"MACP","grabs":13,"pops":17,"drops":12,"hold":60,"captures":1,"prevent":57,"ndpops":5,"returns":4,"tags":4,"pups":3,"minutes":10,"goregrab":3,"longholds":0,"goodhandoff":5,"handoff":7,"coregrab":0,"retinbase":1,"nrtags":0,"holdagainst":230,"pupscomp":27,"pm":-5,"quickret":1,"flaccids":5,"gohandoff":1,"keyret":0,"saves":0,"cohandoff":0,"capspm":0.1,"holdpm":6,"grabspm":1.3,"score%":0.07692307692307693,"holdpgrab":4.615384615384615,"spark%":0.7142857142857143,"flcd%":0.38461538461538464,"tagspm":0.4,"retpm":0.4,"prepm":5.7,"hapm":23,"prepret":14.25,"prepha":0.24782608695652175,"rib%":0.25,"qr%":0.25,"nrtpm":0,"kd":0.23529411764705882,"kf":0,"pup%":0.1111111111111111},"Gman8181":{"score":53,"team":"MACP","grabs":19,"pops":14,"drops":12,"hold":94,"captures":6,"prevent":58,"ndpops":2,"returns":4,"tags":6,"pups":2,"minutes":10,"goregrab":8,"longholds":0,"goodhandoff":3,"handoff":5,"coregrab":1,"retinbase":1,"nrtags":2,"holdagainst":219,"pupscomp":27,"pm":5,"quickret":1,"flaccids":4,"gohandoff":2,"keyret":0,"saves":0,"cohandoff":2,"capspm":0.6,"holdpm":9.4,"grabspm":1.9,"score%":0.3157894736842105,"holdpgrab":4.947368421052632,"spark%":0.6,"flcd%":0.21052631578947367,"tagspm":0.6,"retpm":0.4,"prepm":5.8,"hapm":21.9,"prepret":14.5,"prepha":0.2648401826484018,"rib%":0.25,"qr%":0.25,"nrtpm":0.2,"kd":0.42857142857142855,"kf":1,"pup%":0.07407407407407407},"Fatal":{"score":40,"team":"MACP","grabs":7,"pops":12,"drops":6,"hold":52,"captures":1,"prevent":211,"ndpops":6,"returns":12,"tags":13,"pups":3,"minutes":10,"goregrab":0,"longholds":0,"goodhandoff":1,"handoff":2,"coregrab":0,"retinbase":8,"nrtags":1,"holdagainst":230,"pupscomp":27,"pm":-5,"quickret":7,"flaccids":2,"gohandoff":2,"keyret":0,"saves":0,"cohandoff":1,"capspm":0.1,"holdpm":5.2,"grabspm":0.7,"score%":0.14285714285714285,"holdpgrab":7.428571428571429,"spark%":0.5,"flcd%":0.2857142857142857,"tagspm":1.3,"retpm":1.2,"prepm":21.1,"hapm":23,"prepret":17.583333333333332,"prepha":0.9173913043478261,"rib%":0.6666666666666666,"qr%":0.5833333333333334,"nrtpm":0.1,"kd":1.0833333333333333,"kf":0,"pup%":0.1111111111111111},"Dalek":{"score":42,"team":"MACP","grabs":8,"pops":11,"drops":8,"hold":38,"captures":0,"prevent":149,"ndpops":3,"returns":13,"tags":19,"pups":5,"minutes":10,"goregrab":3,"longholds":1,"goodhandoff":1,"handoff":1,"coregrab":0,"retinbase":9,"nrtags":6,"holdagainst":219,"pupscomp":27,"pm":5,"quickret":10,"flaccids":3,"gohandoff":0,"keyret":0,"saves":0,"cohandoff":0,"capspm":0,"holdpm":3.8,"grabspm":0.8,"score%":0,"holdpgrab":4.75,"spark%":1,"flcd%":0.375,"tagspm":1.9,"retpm":1.3,"prepm":14.9,"hapm":21.9,"prepret":11.461538461538462,"prepha":0.680365296803653,"rib%":0.6923076923076923,"qr%":0.7692307692307693,"nrtpm":0.6,"kd":1.7272727272727273,"kf":0,"pup%":0.18518518518518517},"dywz":{"score":36,"team":"MACP","grabs":18,"pops":18,"drops":16,"hold":77,"captures":2,"prevent":45,"ndpops":2,"returns":4,"tags":6,"pups":6,"minutes":10,"goregrab":3,"longholds":0,"goodhandoff":2,"handoff":4,"coregrab":0,"retinbase":0,"nrtags":2,"holdagainst":219,"pupscomp":27,"pm":5,"quickret":0,"flaccids":8,"gohandoff":5,"keyret":0,"saves":0,"cohandoff":0,"capspm":0.2,"holdpm":7.7,"grabspm":1.8,"score%":0.1111111111111111,"holdpgrab":4.277777777777778,"spark%":0.5,"flcd%":0.4444444444444444,"tagspm":0.6,"retpm":0.4,"prepm":4.5,"hapm":21.9,"prepret":11.25,"prepha":0.2054794520547945,"rib%":0,"qr%":0,"nrtpm":0.2,"kd":0.3333333333333333,"kf":0,"pup%":0.2222222222222222}},"h2":{"danisk":{"score":28,"team":"MACP","grabs":13,"pops":12,"drops":12,"hold":108,"captures":1,"prevent":4,"ndpops":0,"returns":6,"tags":10,"pups":2,"minutes":10,"goregrab":4,"longholds":1,"goodhandoff":2,"handoff":2,"coregrab":0,"retinbase":0,"nrtags":4,"holdagainst":267,"pupscomp":27,"pm":1,"quickret":0,"flaccids":4,"gohandoff":3,"keyret":0,"saves":0,"cohandoff":0,"capspm":0.1,"holdpm":10.8,"grabspm":1.3,"score%":0.07692307692307693,"holdpgrab":8.307692307692308,"spark%":1,"flcd%":0.3076923076923077,"tagspm":1,"retpm":0.6,"prepm":0.4,"hapm":26.7,"prepret":0.6666666666666666,"prepha":0.0149812734082397,"rib%":0,"qr%":0,"nrtpm":0.4,"kd":0.8333333333333334,"kf":0,"pup%":0.07407407407407407},"dywz":{"score":30,"team":"MACP","grabs":16,"pops":17,"drops":15,"hold":135,"captures":1,"prevent":38,"ndpops":2,"returns":3,"tags":7,"pups":3,"minutes":10,"goregrab":2,"longholds":1,"goodhandoff":4,"handoff":5,"coregrab":0,"retinbase":1,"nrtags":4,"holdagainst":271,"pupscomp":27,"pm":-1,"quickret":1,"flaccids":4,"gohandoff":3,"keyret":1,"saves":0,"cohandoff":0,"capspm":0.1,"holdpm":13.5,"grabspm":1.6,"score%":0.0625,"holdpgrab":8.4375,"spark%":0.8,"flcd%":0.25,"tagspm":0.7,"retpm":0.3,"prepm":3.8,"hapm":27.1,"prepret":12.666666666666666,"prepha":0.14022140221402213,"rib%":0.3333333333333333,"qr%":0.3333333333333333,"nrtpm":0.4,"kd":0.4117647058823529,"kf":0,"pup%":0.1111111111111111},"Gman8181":{"score":22,"team":"MACP","grabs":15,"pops":16,"drops":13,"hold":94,"captures":2,"prevent":31,"ndpops":3,"returns":3,"tags":3,"pups":1,"minutes":10,"goregrab":3,"longholds":0,"goodhandoff":4,"handoff":7,"coregrab":0,"retinbase":2,"nrtags":0,"holdagainst":271,"pupscomp":27,"pm":-1,"quickret":1,"flaccids":3,"gohandoff":1,"keyret":0,"saves":0,"cohandoff":0,"capspm":0.2,"holdpm":9.4,"grabspm":1.5,"score%":0.13333333333333333,"holdpgrab":6.266666666666667,"spark%":0.5714285714285714,"flcd%":0.2,"tagspm":0.3,"retpm":0.3,"prepm":3.1,"hapm":27.1,"prepret":10.333333333333334,"prepha":0.11439114391143912,"rib%":0.6666666666666666,"qr%":0.3333333333333333,"nrtpm":0,"kd":0.1875,"kf":0,"pup%":0.037037037037037035},"#Frozen":{"score":39,"team":"MACP","grabs":16,"pops":18,"drops":13,"hold":93,"captures":2,"prevent":33,"ndpops":5,"returns":7,"tags":10,"pups":6,"minutes":10,"goregrab":2,"longholds":1,"goodhandoff":7,"handoff":8,"coregrab":1,"retinbase":4,"nrtags":3,"holdagainst":267,"pupscomp":27,"pm":1,"quickret":2,"flaccids":5,"gohandoff":1,"keyret":0,"saves":0,"cohandoff":0,"capspm":0.2,"holdpm":9.3,"grabspm":1.6,"score%":0.125,"holdpgrab":5.8125,"spark%":0.875,"flcd%":0.3125,"tagspm":1,"retpm":0.7,"prepm":3.3,"hapm":26.7,"prepret":4.714285714285714,"prepha":0.12359550561797752,"rib%":0.5714285714285714,"qr%":0.2857142857142857,"nrtpm":0.3,"kd":0.5555555555555556,"kf":1,"pup%":0.2222222222222222},"Fatal":{"score":54,"team":"MACP","grabs":9,"pops":10,"drops":7,"hold":42,"captures":2,"prevent":181,"ndpops":3,"returns":10,"tags":14,"pups":6,"minutes":10,"goregrab":3,"longholds":0,"goodhandoff":0,"handoff":0,"coregrab":1,"retinbase":7,"nrtags":4,"holdagainst":267,"pupscomp":27,"pm":1,"quickret":6,"flaccids":4,"gohandoff":0,"keyret":0,"saves":0,"cohandoff":0,"capspm":0.2,"holdpm":4.2,"grabspm":0.9,"score%":0.2222222222222222,"holdpgrab":4.666666666666667,"spark%":0,"flcd%":0.4444444444444444,"tagspm":1.4,"retpm":1,"prepm":18.1,"hapm":26.7,"prepret":18.1,"prepha":0.6779026217228464,"rib%":0.7,"qr%":0.6,"nrtpm":0.4,"kd":1.4,"kf":0,"pup%":0.2222222222222222},"sIide":{"score":41,"team":"MACP","grabs":6,"pops":11,"drops":6,"hold":19,"captures":0,"prevent":163,"ndpops":5,"returns":16,"tags":20,"pups":4,"minutes":10,"goregrab":2,"longholds":0,"goodhandoff":1,"handoff":2,"coregrab":0,"retinbase":10,"nrtags":4,"holdagainst":271,"pupscomp":27,"pm":-1,"quickret":9,"flaccids":2,"gohandoff":1,"keyret":1,"saves":0,"cohandoff":0,"capspm":0,"holdpm":1.9,"grabspm":0.6,"score%":0,"holdpgrab":3.1666666666666665,"spark%":0.5,"flcd%":0.3333333333333333,"tagspm":2,"retpm":1.6,"prepm":16.3,"hapm":27.1,"prepret":10.1875,"prepha":0.6014760147601476,"rib%":0.625,"qr%":0.5625,"nrtpm":0.4,"kd":1.8181818181818181,"kf":0,"pup%":0.14814814814814814},"Dalek":{"score":42,"team":"MACP","grabs":7,"pops":8,"drops":5,"hold":19,"captures":1,"prevent":197,"ndpops":3,"returns":14,"tags":14,"pups":2,"minutes":10,"goregrab":4,"longholds":0,"goodhandoff":0,"handoff":0,"coregrab":1,"retinbase":4,"nrtags":0,"holdagainst":271,"pupscomp":27,"pm":-1,"quickret":4,"flaccids":4,"gohandoff":1,"keyret":0,"saves":0,"cohandoff":0,"capspm":0.1,"holdpm":1.9,"grabspm":0.7,"score%":0.14285714285714285,"holdpgrab":2.7142857142857144,"spark%":0,"flcd%":0.5714285714285714,"tagspm":1.4,"retpm":1.4,"prepm":19.7,"hapm":27.1,"prepret":14.071428571428571,"prepha":0.7269372693726938,"rib%":0.2857142857142857,"qr%":0.2857142857142857,"nrtpm":0,"kd":1.75,"kf":1,"pup%":0.07407407407407407},"CB13":{"score":44,"team":"MACP","grabs":4,"pops":6,"drops":4,"hold":28,"captures":0,"prevent":186,"ndpops":2,"returns":16,"tags":18,"pups":3,"minutes":10,"goregrab":0,"longholds":1,"goodhandoff":0,"handoff":2,"coregrab":0,"retinbase":6,"nrtags":2,"holdagainst":267,"pupscomp":27,"pm":1,"quickret":5,"flaccids":2,"gohandoff":0,"keyret":1,"saves":0,"cohandoff":0,"capspm":0,"holdpm":2.8,"grabspm":0.4,"score%":0,"holdpgrab":7,"spark%":0,"flcd%":0.5,"tagspm":1.8,"retpm":1.6,"prepm":18.6,"hapm":26.7,"prepret":11.625,"prepha":0.6966292134831461,"rib%":0.375,"qr%":0.3125,"nrtpm":0.2,"kd":3,"kf":0,"pup%":0.1111111111111111}},"ot":{},"total":{"danisk":{"score":53,"team":"MACP","grabs":32,"pops":31,"drops":30,"hold":199,"captures":1,"prevent":35,"ndpops":1,"returns":19,"tags":26,"pups":3,"minutes":20,"goregrab":8,"longholds":1,"goodhandoff":5,"handoff":10,"coregrab":0,"retinbase":6,"nrtags":7,"holdagainst":497,"pupscomp":54,"pm":-4,"quickret":4,"flaccids":8,"gohandoff":6,"keyret":1,"saves":0,"cohandoff":0,"capspm":0.05,"holdpm":9.95,"grabspm":1.6,"score%":0.03125,"holdpgrab":6.21875,"spark%":0.5,"flcd%":0.25,"tagspm":1.3,"retpm":0.95,"prepm":1.75,"hapm":24.85,"prepret":1.8421052631578947,"prepha":0.07042253521126761,"rib%":0.3157894736842105,"qr%":0.21052631578947367,"nrtpm":0.35,"kd":0.8387096774193549,"kf":1,"pup%":0.05555555555555555},"CB13":{"score":79,"team":"MACP","grabs":11,"pops":18,"drops":10,"hold":44,"captures":1,"prevent":354,"ndpops":8,"returns":28,"tags":31,"pups":5,"minutes":20,"goregrab":2,"longholds":1,"goodhandoff":0,"handoff":2,"coregrab":1,"retinbase":13,"nrtags":3,"holdagainst":497,"pupscomp":54,"pm":-4,"quickret":11,"flaccids":7,"gohandoff":0,"keyret":1,"saves":0,"cohandoff":0,"capspm":0.05,"holdpm":2.2,"grabspm":0.55,"score%":0.09090909090909091,"holdpgrab":4,"spark%":0,"flcd%":0.6363636363636364,"tagspm":1.55,"retpm":1.4,"prepm":17.7,"hapm":24.85,"prepret":12.642857142857142,"prepha":0.7122736418511066,"rib%":0.4642857142857143,"qr%":0.39285714285714285,"nrtpm":0.15,"kd":1.7222222222222223,"kf":0,"pup%":0.09259259259259259},"sIide":{"score":90,"team":"MACP","grabs":12,"pops":19,"drops":12,"hold":40,"captures":0,"prevent":361,"ndpops":7,"returns":37,"tags":45,"pups":9,"minutes":20,"goregrab":3,"longholds":0,"goodhandoff":3,"handoff":4,"coregrab":0,"retinbase":17,"nrtags":8,"holdagainst":490,"pupscomp":54,"pm":4,"quickret":14,"flaccids":5,"gohandoff":1,"keyret":2,"saves":1,"cohandoff":0,"capspm":0,"holdpm":2,"grabspm":0.6,"score%":0,"holdpgrab":3.3333333333333335,"spark%":0.75,"flcd%":0.4166666666666667,"tagspm":2.25,"retpm":1.85,"prepm":18.05,"hapm":24.5,"prepret":9.756756756756756,"prepha":0.736734693877551,"rib%":0.4594594594594595,"qr%":0.3783783783783784,"nrtpm":0.4,"kd":2.3684210526315788,"kf":0,"pup%":0.16666666666666666},"#Frozen":{"score":59,"team":"MACP","grabs":29,"pops":35,"drops":25,"hold":153,"captures":3,"prevent":90,"ndpops":10,"returns":11,"tags":14,"pups":9,"minutes":20,"goregrab":5,"longholds":1,"goodhandoff":12,"handoff":15,"coregrab":1,"retinbase":5,"nrtags":3,"holdagainst":497,"pupscomp":54,"pm":-4,"quickret":3,"flaccids":10,"gohandoff":2,"keyret":0,"saves":0,"cohandoff":0,"capspm":0.15,"holdpm":7.65,"grabspm":1.45,"score%":0.10344827586206896,"holdpgrab":5.275862068965517,"spark%":0.8,"flcd%":0.3448275862068966,"tagspm":0.7,"retpm":0.55,"prepm":4.5,"hapm":24.85,"prepret":8.181818181818182,"prepha":0.18108651911468812,"rib%":0.45454545454545453,"qr%":0.2727272727272727,"nrtpm":0.15,"kd":0.4,"kf":1,"pup%":0.16666666666666666},"Gman8181":{"score":75,"team":"MACP","grabs":34,"pops":30,"drops":25,"hold":188,"captures":8,"prevent":89,"ndpops":5,"returns":7,"tags":9,"pups":3,"minutes":20,"goregrab":11,"longholds":0,"goodhandoff":7,"handoff":12,"coregrab":1,"retinbase":3,"nrtags":2,"holdagainst":490,"pupscomp":54,"pm":4,"quickret":2,"flaccids":7,"gohandoff":3,"keyret":0,"saves":0,"cohandoff":2,"capspm":0.4,"holdpm":9.4,"grabspm":1.7,"score%":0.23529411764705882,"holdpgrab":5.529411764705882,"spark%":0.5833333333333334,"flcd%":0.20588235294117646,"tagspm":0.45,"retpm":0.35,"prepm":4.45,"hapm":24.5,"prepret":12.714285714285714,"prepha":0.1816326530612245,"rib%":0.42857142857142855,"qr%":0.2857142857142857,"nrtpm":0.1,"kd":0.3,"kf":1,"pup%":0.05555555555555555},"Fatal":{"score":94,"team":"MACP","grabs":16,"pops":22,"drops":13,"hold":94,"captures":3,"prevent":392,"ndpops":9,"returns":22,"tags":27,"pups":9,"minutes":20,"goregrab":3,"longholds":0,"goodhandoff":1,"handoff":2,"coregrab":1,"retinbase":15,"nrtags":5,"holdagainst":497,"pupscomp":54,"pm":-4,"quickret":13,"flaccids":6,"gohandoff":2,"keyret":0,"saves":0,"cohandoff":1,"capspm":0.15,"holdpm":4.7,"grabspm":0.8,"score%":0.1875,"holdpgrab":5.875,"spark%":0.5,"flcd%":0.375,"tagspm":1.35,"retpm":1.1,"prepm":19.6,"hapm":24.85,"prepret":17.818181818181817,"prepha":0.7887323943661971,"rib%":0.6818181818181818,"qr%":0.5909090909090909,"nrtpm":0.25,"kd":1.2272727272727273,"kf":0,"pup%":0.16666666666666666},"Dalek":{"score":84,"team":"MACP","grabs":15,"pops":19,"drops":13,"hold":57,"captures":1,"prevent":346,"ndpops":6,"returns":27,"tags":33,"pups":7,"minutes":20,"goregrab":7,"longholds":1,"goodhandoff":1,"handoff":1,"coregrab":1,"retinbase":13,"nrtags":6,"holdagainst":490,"pupscomp":54,"pm":4,"quickret":14,"flaccids":7,"gohandoff":1,"keyret":0,"saves":0,"cohandoff":0,"capspm":0.05,"holdpm":2.85,"grabspm":0.75,"score%":0.06666666666666667,"holdpgrab":3.8,"spark%":1,"flcd%":0.4666666666666667,"tagspm":1.65,"retpm":1.35,"prepm":17.3,"hapm":24.5,"prepret":12.814814814814815,"prepha":0.7061224489795919,"rib%":0.48148148148148145,"qr%":0.5185185185185185,"nrtpm":0.3,"kd":1.736842105263158,"kf":1,"pup%":0.12962962962962962},"dywz":{"score":66,"team":"MACP","grabs":34,"pops":35,"drops":31,"hold":212,"captures":3,"prevent":83,"ndpops":4,"returns":7,"tags":13,"pups":9,"minutes":20,"goregrab":5,"longholds":1,"goodhandoff":6,"handoff":9,"coregrab":0,"retinbase":1,"nrtags":6,"holdagainst":490,"pupscomp":54,"pm":4,"quickret":1,"flaccids":12,"gohandoff":8,"keyret":1,"saves":0,"cohandoff":0,"capspm":0.15,"holdpm":10.6,"grabspm":1.7,"score%":0.08823529411764706,"holdpgrab":6.235294117647059,"spark%":0.6666666666666666,"flcd%":0.35294117647058826,"tagspm":0.65,"retpm":0.35,"prepm":4.15,"hapm":24.5,"prepret":11.857142857142858,"prepha":0.16938775510204082,"rib%":0.14285714285714285,"qr%":0.14285714285714285,"nrtpm":0.3,"kd":0.37142857142857144,"kf":0,"pup%":0.16666666666666666}}}}}